sparql_query_tools/ParseSparqlJsonResult.py
sparql_query_tools/RunQuery.py
sparql_query_tools/__init__.py
sparql_query_tools/commons.py
sparql_query_tools/clickextension/IntList.py
sparql_query_tools/clickextension/QueryFilesParam.py
sparql_query_tools/clickextension/URLParam.py
sparql_query_tools/clickextension/__init__.py
sparql_query_tools/sparql_result_analysis/__init__.py
sparql_query_tools/sparql_result_analysis/run.py
sparql_query_tools-0.1.9.dist-info/LICENSE.md
sparql_query_tools-0.1.9.dist-info/METADATA
sparql_query_tools-0.1.9.dist-info/WHEEL
sparql_query_tools-0.1.9.dist-info/entry_points.txt
sparql_query_tools-0.1.9.dist-info/top_level.txt
sparql_query_tools-0.1.9.dist-info/RECORD
