Metadata-Version: 2.1
Name: sparql-query-tools
Version: 0.1.9
Summary: tools to run SPARQL queries and get metrics.
Home-page: https://github.com/dice-group/sparql-query-tools
Author: Alexander Bigerl
Author-email: info@dice-research.org
License: AGPL v3
Platform: UNKNOWN
Classifier: Programming Language :: Python :: 3.6
Classifier: License :: OSI Approved :: GNU Affero General Public License v3 or later (AGPLv3+)
Requires-Python: >=3.6
Requires-Dist: rdflib (>=5.0.0)
Requires-Dist: requests (>=2.25.1)
Requires-Dist: click (>=7.1.2)
Requires-Dist: pycurl (>=7.43.0.6)
